MANIFEST.in
setup.py
bin/mineCommits.py
git2mine/__init__.py
git2mine/gitReader.py
git2mine/mainGit2mine.py
git2mine/redmineWriter.py
git2mine.egg-info/PKG-INFO
git2mine.egg-info/SOURCES.txt
git2mine.egg-info/dependency_links.txt
git2mine.egg-info/not-zip-safe
git2mine.egg-info/requires.txt
git2mine.egg-info/top_level.txt
git2mine/frontend/git2mine.glade