Metadata-Version: 1.0
Name: git2mine
Version: 0.3
Summary: A python application aimed to make easier the tedious task of logging time for Redmine tasks by extracting information from GIT commits comments
Home-page: http://github.com/pfcoperez/git2mine
Author: Pablo Francisco Perez Hidalgo
Author-email: contact@pablofranciscoperez.info
License: GPLV2
Platform: UNKNOWN
